checker_players/__init__.py
checker_players/Checker_Environment/Board.py
checker_players/Checker_Environment/__init__.py
checker_players/Interpretters/DoubleColumnInterpretter.py
checker_players/Interpretters/FlatFeaturesInterpretter.py
checker_players/Interpretters/Interpretter.py
checker_players/Interpretters/__init__.py
checker_players/Players/AlphaBeta.py
checker_players/Players/DQNPlayer.py
checker_players/Players/MinimaxPlayer.py
checker_players/Players/MultilayerPerceptron.py
checker_players/Players/Player.py
checker_players/Players/RandomPlayer.py
checker_players/Players/__init__.py
checker_players/Runners/TestRunner.py
checker_players/Runners/TrainRunner.py
checker_players/Runners/__init__.py
checker_players/Runners/Loggers/Logger.py
checker_players/Runners/Loggers/SimpleLogger.py
checker_players/Runners/Loggers/TrainLogger.py
checker_players/Runners/Loggers/__init__.py
checker_players-1.0.4.dist-info/METADATA
checker_players-1.0.4.dist-info/WHEEL
checker_players-1.0.4.dist-info/licenses/LICENSE.txt
checker_players-1.0.4.dist-info/RECORD
